stataLogObject/__init__.py
stataLogObject/Configs/ConfigObj.py
stataLogObject/Configs/Extractors.py
stataLogObject/Configs/ModelFit.py
stataLogObject/Configs/ModelVars.py
stataLogObject/Configs/TableEntries.py
stataLogObject/Configs/VariableHolders.py
stataLogObject/Configs/__init__.py
stataLogObject/StataParser/StataLog.py
stataLogObject/StataParser/StataRaw.py
stataLogObject/StataParser/StataTable.py
stataLogObject/StataParser/__init__.py
stataLogObject/Supports/Errors.py
stataLogObject/Supports/__init__.py
stataLogObject/Supports/supports.py
stataLogObject-0.2.2.dist-info/LICENSE
stataLogObject-0.2.2.dist-info/METADATA
stataLogObject-0.2.2.dist-info/WHEEL
stataLogObject-0.2.2.dist-info/top_level.txt
stataLogObject-0.2.2.dist-info/RECORD
